postgresql_setrole/__init__.py
postgresql_setrole/apps.py
django_postgresql_setrole-1.0.12.dist-info/LICENSE
django_postgresql_setrole-1.0.12.dist-info/METADATA
django_postgresql_setrole-1.0.12.dist-info/WHEEL
django_postgresql_setrole-1.0.12.dist-info/top_level.txt
django_postgresql_setrole-1.0.12.dist-info/RECORD
